rekt/__init__.py
rekt/rekt.py
rekt/rekt_fast.py
rekt/rektaa.py
rekt/rektlvls.py
vs_rekt-1.0.0.dist-info/LICENSE
vs_rekt-1.0.0.dist-info/METADATA
vs_rekt-1.0.0.dist-info/WHEEL
vs_rekt-1.0.0.dist-info/top_level.txt
vs_rekt-1.0.0.dist-info/RECORD
